README.md
setup.cfg
setup.py
distributions_mariolys/Binomialdistribution.py
distributions_mariolys/Gaussiandistribution.py
distributions_mariolys/Generaldistribution.py
distributions_mariolys/__init__.py
distributions_mariolys.egg-info/PKG-INFO
distributions_mariolys.egg-info/SOURCES.txt
distributions_mariolys.egg-info/dependency_links.txt
distributions_mariolys.egg-info/not-zip-safe
distributions_mariolys.egg-info/top_level.txt